arronax/__init__.py
arronax/_meta.py
arronax/about.py
arronax/appbrowser.py
arronax/categoriesbrowser.py
arronax/clipboard.py
arronax/desktopfile.py
arronax/dialogs.py
arronax/editor.py
arronax/entrytools.py
arronax/filechooser.py
arronax/iconbrowser.py
arronax/mimetypes.py
arronax/parsecli.py
arronax/plugin.py
arronax/quicklist.py
arronax/settings.py
arronax/statusbar.py
arronax/tvtools.py
arronax/utils.py
arronax/xdgdirs.py
arronax/xdgpath.py
arronax-0.7.1.data/data/share/applications/arronax.desktop
arronax-0.7.1.data/data/share/arronax/ui/appbrowser.ui
arronax-0.7.1.data/data/share/arronax/ui/categoriesdlg.ui
arronax-0.7.1.data/data/share/arronax/ui/edit.ui
arronax-0.7.1.data/data/share/arronax/ui/icondlg.ui
arronax-0.7.1.data/data/share/arronax/ui/mimetypes.ui
arronax-0.7.1.data/data/share/arronax/ui/quicklist.ui
arronax-0.7.1.data/data/share/caja-python/extensions/caja-arronax.py
arronax-0.7.1.data/data/share/icons/hicolor/128x128/arronax.png
arronax-0.7.1.data/data/share/icons/hicolor/16x16/arronax.png
arronax-0.7.1.data/data/share/icons/hicolor/192x192/arronax.png
arronax-0.7.1.data/data/share/icons/hicolor/22x22/arronax.png
arronax-0.7.1.data/data/share/icons/hicolor/24x24/arronax.png
arronax-0.7.1.data/data/share/icons/hicolor/256x256/arronax.png
arronax-0.7.1.data/data/share/icons/hicolor/28x28/arronax.png
arronax-0.7.1.data/data/share/icons/hicolor/32x32/arronax.png
arronax-0.7.1.data/data/share/icons/hicolor/36x36/arronax.png
arronax-0.7.1.data/data/share/icons/hicolor/48x48/arronax.png
arronax-0.7.1.data/data/share/icons/hicolor/64x64/arronax.png
arronax-0.7.1.data/data/share/icons/hicolor/72x72/arronax.png
arronax-0.7.1.data/data/share/icons/hicolor/96x96/arronax.png
arronax-0.7.1.data/data/share/icons/hicolor/scalable/apps/arronax.svg
arronax-0.7.1.data/data/share/locale/bg/LC_MESSAGES/arronax.mo
arronax-0.7.1.data/data/share/locale/ca/LC_MESSAGES/arronax.mo
arronax-0.7.1.data/data/share/locale/cs/LC_MESSAGES/arronax.mo
arronax-0.7.1.dist-info/COPYING
arronax-0.7.1.dist-info/METADATA
arronax-0.7.1.dist-info/WHEEL
arronax-0.7.1.dist-info/entry_points.txt
arronax-0.7.1.dist-info/top_level.txt
arronax-0.7.1.dist-info/RECORD
