Metadata-Version: 2.1
Name: arronax
Version: 0.7.1
Summary: Create and modify application, file and URI starters.
Home-page: https://www.florian-diesch.de/software/arronax/
Author: Florian Diesch
Author-email: devel@florian-diesch.de
Maintainer: Florian Diesch
Maintainer-email: devel@florian-diesch.de
License: UNKNOWN
Download-URL: https://www.florian-diesch.de/software/arronax/
Keywords: Nautilus,Nemo,Caja,extension,plugin,starter,desktop
Platform: UNKNOWN
Classifier: Environment :: X11 Applications :: GTK
Classifier: Intended Audience :: End Users/Desktop
Classifier: License :: OSI Approved :: GNU General Public License v3 or later (GPLv3+)
Classifier: Natural Language :: English
Classifier: Natural Language :: German
Classifier: Operating System :: POSIX :: Linux
Classifier: Programming Language :: Python :: 3
Classifier: Topic :: Utilities
